mefs_utils/__init__.py
mefs_utils/analysis.py
mefs_utils/rosters.py
wf_mefs_utils-1.8.0.dist-info/LICENSE
wf_mefs_utils-1.8.0.dist-info/METADATA
wf_mefs_utils-1.8.0.dist-info/WHEEL
wf_mefs_utils-1.8.0.dist-info/top_level.txt
wf_mefs_utils-1.8.0.dist-info/RECORD
