Metadata-Version: 2.1
Name: wf-mefs-utils
Version: 1.8.0
Summary: Tools for working with MEFS/EFgo assessments data
Home-page: https://github.com/WildflowerSchools/wf-mefs-utils
Author: Theodore Quinn
Author-email: ted.quinn@wildflowerschools.org
License: UNKNOWN
Keywords: database
Platform: UNKNOWN
Classifier: Intended Audience :: Developers
Classifier: License :: OSI Approved :: MIT License
Classifier: Operating System :: OS Independent
Classifier: Programming Language :: Python
Requires-Dist: numpy (>=1.19)
Requires-Dist: pandas (>=1.3)
Requires-Dist: wf-core-data-python (>=1.3.0)
